skdownscale/__init__.py
skdownscale/pointwise_models/__init__.py
skdownscale/pointwise_models/arrm.py
skdownscale/pointwise_models/base.py
skdownscale/pointwise_models/bcsd.py
skdownscale/pointwise_models/core.py
skdownscale/pointwise_models/gard.py
skdownscale/pointwise_models/groupers.py
skdownscale/pointwise_models/grouping.py
skdownscale/pointwise_models/quantile.py
skdownscale/pointwise_models/trend.py
skdownscale/pointwise_models/utils.py
skdownscale/pointwise_models/zscore.py
scikit_downscale-0.1.5.dist-info/LICENSE
scikit_downscale-0.1.5.dist-info/METADATA
scikit_downscale-0.1.5.dist-info/WHEEL
scikit_downscale-0.1.5.dist-info/top_level.txt
scikit_downscale-0.1.5.dist-info/RECORD
