Metadata-Version: 2.1
Name: scikit-downscale
Version: 0.1.5
Summary: Statistical downscaling and postprocessing models for climate and weather model simulations.
Home-page: https://github.com/jhamman/scikit-downscale
Author: Joe Hamman
Author-email: jhamman@ucar.edu
License: Apache
Platform: UNKNOWN
Classifier: Development Status :: 2 - Pre-Alpha
Classifier: License :: OSI Approved :: Apache Software License
Classifier: Operating System :: OS Independent
Classifier: Intended Audience :: Science/Research
Classifier: Programming Language :: Python
Classifier: Programming Language :: Python :: 3
Classifier: Programming Language :: Python :: 3.6
Classifier: Programming Language :: Python :: 3.7
Classifier: Programming Language :: Python :: 3.8
Classifier: Topic :: Scientific/Engineering
Requires-Python: >=3.6
Requires-Dist: xarray (>=0.16)
Requires-Dist: scikit-learn (>=0.21)
